tscleaner/__init__.py
tscleaner/cleaner.py
tscleaner/dataframe.py
tscleaner/error.py
tscleaner/figure_plotter.py
tscleaner/loop_files.py
tscleaner/reservoir_series.py
tscleaner-0.1.0.dist-info/AUTHORS.rst
tscleaner-0.1.0.dist-info/LICENSE
tscleaner-0.1.0.dist-info/METADATA
tscleaner-0.1.0.dist-info/WHEEL
tscleaner-0.1.0.dist-info/top_level.txt
tscleaner-0.1.0.dist-info/RECORD
